duyai/__init__.py
duyai/cv/__init__.py
duyai/cv/base_cnn/__init__.py
duyai/cv/base_cnn/autoencoder.py
duyai/cv/base_cnn/facenet.py
duyai/cv/base_cnn/fpn.py
duyai/cv/base_cnn/inception_resnet_v1.py
duyai/cv/base_cnn/resnet.py
duyai/cv/base_cnn/vgg.py
duyai/cv/face/__init__.py
duyai/cv/face/detection.py
duyai/cv/face/distance.py
duyai/cv/face/extraction.py
duyai/cv/object_detection/__init__.py
duyai/cv/object_detection/detection.py
duyai/cv/object_detection/yolo.py
duyai/cv/object_detection/yolo3/__init__.py
duyai/cv/object_detection/yolo3/model.py
duyai/cv/object_detection/yolo3/utils.py
duyai/cv/object_tracking/__init__.py
duyai/cv/object_tracking/track.py
duyai/cv/object_tracking/deep_sort/__init__.py
duyai/cv/object_tracking/deep_sort/detection.py
duyai/cv/object_tracking/deep_sort/iou_matching.py
duyai/cv/object_tracking/deep_sort/kalman_filter.py
duyai/cv/object_tracking/deep_sort/linear_assignment.py
duyai/cv/object_tracking/deep_sort/nn_matching.py
duyai/cv/object_tracking/deep_sort/preprocessing.py
duyai/cv/object_tracking/deep_sort/track.py
duyai/cv/object_tracking/deep_sort/tracker.py
duyai/cv/object_tracking/tools/__init__.py
duyai/cv/object_tracking/tools/freeze_model.py
duyai/cv/object_tracking/tools/generate_detections.py
duyai/cv/utils/__init__.py
duyai/cv/utils/model_utils.py
duyai/cv/utils/mtcnntf/__init__.py
duyai/cv/utils/mtcnntf/models.py
duyai/cv/utils/mtcnntf/utils.py
duyai-0.1.3.dist-info/LICENSE
duyai-0.1.3.dist-info/METADATA
duyai-0.1.3.dist-info/WHEEL
duyai-0.1.3.dist-info/top_level.txt
duyai-0.1.3.dist-info/RECORD
