Metadata-Version: 2.1
Name: duyai
Version: 0.1.3
Summary: Describe your package in one sentence
Home-page: https://github.com/DuyKK/duyai
Author: Duy Nguyen Manh
Author-email: manhduy160396@email.com
License: MIT License
Platform: UNKNOWN
License-File: LICENSE
Requires-Dist: opencv-python
Requires-Dist: gdown
